py_version_from_tag/__init__.py
py_version_from_tag/__main__.py
py_version_from_tag/utils.py
py_version_from_tag-1.2.0.dist-info/LICENSE
py_version_from_tag-1.2.0.dist-info/METADATA
py_version_from_tag-1.2.0.dist-info/WHEEL
py_version_from_tag-1.2.0.dist-info/entry_points.txt
py_version_from_tag-1.2.0.dist-info/top_level.txt
py_version_from_tag-1.2.0.dist-info/RECORD
