Metadata-Version: 2.1
Name: py-version-from-tag
Version: 1.2.0
Summary: A simple tool to automatically write git tag name to version field of python setup files.
Author-email: Jost Prevc <jost.prevc@gmail.com>
License: MIT
Keywords: git,tag,setup,build,pyproject.toml
Classifier: Programming Language :: Python :: 3
Requires-Python: >=3.7
License-File: LICENSE
Requires-Dist: toml
Provides-Extra: dev
Requires-Dist: pytest ; extra == 'dev'
Requires-Dist: pylint ; extra == 'dev'
Requires-Dist: pre-commit ; extra == 'dev'
Requires-Dist: black[d] ; extra == 'dev'
Requires-Dist: mypy ; extra == 'dev'
Requires-Dist: tox ; extra == 'dev'
Requires-Dist: types-toml ; extra == 'dev'
Provides-Extra: test
Requires-Dist: pytest ; extra == 'test'
